leann/__init__.py
leann/api.py
leann/chat.py
leann/chunking_utils.py
leann/cli.py
leann/embedding_compute.py
leann/embedding_server_manager.py
leann/interactive_utils.py
leann/interface.py
leann/mcp.py
leann/metadata_filter.py
leann/registry.py
leann/searcher_base.py
leann/settings.py
leann_core-0.3.6.dist-info/METADATA
leann_core-0.3.6.dist-info/WHEEL
leann_core-0.3.6.dist-info/entry_points.txt
leann_core-0.3.6.dist-info/top_level.txt
leann_core-0.3.6.dist-info/RECORD
